mcp_server_rabel/__init__.py
mcp_server_rabel/__main__.py
mcp_server_rabel/server.py
mcp_server_rabel-0.3.2.dist-info/METADATA
mcp_server_rabel-0.3.2.dist-info/WHEEL
mcp_server_rabel-0.3.2.dist-info/entry_points.txt
mcp_server_rabel-0.3.2.dist-info/licenses/LICENSE
mcp_server_rabel-0.3.2.dist-info/RECORD
