Metadata-Version: 2.4
Name: mcp-server-rabel
Version: 0.3.2
Summary: RABEL - Recidive Active Brain Environment Layer. Local-first AI memory with semantic search, graph relations, and soft pipelines. Now with Remote Mode for cross-machine AI communication!
Project-URL: Homepage, https://humotica.com
Project-URL: Repository, https://github.com/jaspertvdm/mcp-server-rabel
Project-URL: Documentation, https://github.com/jaspertvdm/mcp-server-rabel#readme
Author-email: Jasper van de Meent <info@humotica.com>, "Root AI (Claude)" <root_ai@humotica.nl>
License-Expression: AGPL-3.0-or-later
License-File: LICENSE
Keywords: ai,humotica,knowledge-graph,local-first,mcp,memory,rabel,semantic-search
Classifier: Development Status :: 4 - Beta
Classifier: Intended Audience :: Developers
Classifier: License :: OSI Approved :: GNU Affero General Public License v3
Classifier: Programming Language :: Python :: 3
Classifier: Programming Language :: Python :: 3.10
Classifier: Programming Language :: Python :: 3.11
Classifier: Programming Language :: Python :: 3.12
Classifier: Topic :: Scientific/Engineering :: Artificial Intelligence
Requires-Python: >=3.10
Requires-Dist: mcp>=1.0.0
Requires-Dist: requests>=2.28.0
Provides-Extra: full
Requires-Dist: requests>=2.28.0; extra == 'full'
Requires-Dist: sqlite-vec>=0.1.0; extra == 'full'
Provides-Extra: vector
Requires-Dist: requests>=2.28.0; extra == 'vector'
Requires-Dist: sqlite-vec>=0.1.0; extra == 'vector'
